{"data": [{"public_metrics": {"retweet_count": 0, "reply_count": 0, "like_count": 0, "quote_count": 0}, "id": "1050397632764567553", "author_id": "977668643965222913", "lang": "en", "created_at": "2018-10-11T14:48:05.000Z", "in_reply_to_user_id": "846864187015888896", "text": "@TheBlastNews That could be any homeless person..."}, {"public_metrics": {"retweet_count": 0, "reply_count": 0, "like_count": 0, "quote_count": 0}, "id": "1050389564135800832", "author_id": "917400851093905409", "lang": "en", "created_at": "2018-10-11T14:16:02.000Z", "in_reply_to_user_id": "28816309", "text": "@Dina921 @TheBlastNews Yes it\u2019s ridiculous."}, {"public_metrics": {"retweet_count": 0, "reply_count": 1, "like_count": 2, "quote_count": 0}, "id": "1050386927726338048", "author_id": "917400851093905409", "lang": "en", "created_at": "2018-10-11T14:05:33.000Z", "in_reply_to_user_id": "846864187015888896", "text": "@TheBlastNews \ud83d\ude44  stop connecting these two. He goes to church every Wednesday and there\u2019s video of him leaving and smiling. And Hailey was working. That\u2019s why she wasn\u2019t there"}], "meta": {"newest_id": "1050397632764567553", "oldest_id": "1050386927726338048", "result_count": 3}}