{"data": [{"public_metrics": {"retweet_count": 0, "reply_count": 0, "like_count": 1, "quote_count": 0}, "author_id": "807333467528761345", "lang": "en", "id": "968567027312013314", "in_reply_to_user_id": "2548619438", "created_at": "2018-02-27T19:22:29.000Z", "text": "@Dawson_Coyle #TeamDawson will live on\ud83d\ude4c\u270c\ufe0fshine bright, Dawsey Boy \u2728\ud83d\udc99\ud83d\udc99"}, {"public_metrics": {"retweet_count": 0, "reply_count": 0, "like_count": 2, "quote_count": 0}, "author_id": "1122397387", "lang": "en", "id": "968556961150177280", "in_reply_to_user_id": "2548619438", "created_at": "2018-02-27T18:42:29.000Z", "text": "@Dawson_Coyle @NBCTheVoice @aliciakeys @blakeshelton @LukeBryanOnline @adamlevine @gwenstefani Yes! How time is flying fast!! Omg, I miss season 12 and I miss you on the voice SO MUCH, but I can\u2019t wait to watch season 14 \ud83d\ude0d\ud83d\ude0d\ud83d\ude0d LOVE YOU DAWSON"}], "meta": {"newest_id": "968567027312013314", "oldest_id": "968556961150177280", "result_count": 2}}