{"data": [{"lang": "en", "created_at": "2018-10-09T13:43:50.000Z", "id": "1049656686041071616", "in_reply_to_user_id": "1044695544973676545", "public_metrics": {"retweet_count": 0, "reply_count": 0, "like_count": 0, "quote_count": 0}, "text": "@AdairBlackmore @MirrorCeleb @DailyMirror \"work\"... Her poor father must be rolling in his grave. No matter what we might think of his position on OJ, at least he had standards.", "author_id": "2840739262"}, {"lang": "en", "created_at": "2018-10-09T01:07:26.000Z", "id": "1049466332398448643", "in_reply_to_user_id": "55204143", "public_metrics": {"retweet_count": 0, "reply_count": 0, "like_count": 0, "quote_count": 0}, "text": "@MirrorCeleb NO COMMENTS .......SPEAKS VOLUMES.!!", "author_id": "2560953854"}], "meta": {"newest_id": "1049656686041071616", "oldest_id": "1049466332398448643", "result_count": 2}}