{"data": [{"id": "1050945152754339840", "public_metrics": {"retweet_count": 0, "reply_count": 0, "like_count": 1, "quote_count": 0}, "in_reply_to_user_id": "367866510", "created_at": "2018-10-13T03:03:44.000Z", "lang": "und", "author_id": "188078998", "text": "@jkmcnary1 https://t.co/eZdBHfWbc8"}, {"id": "1050941415105200128", "public_metrics": {"retweet_count": 0, "reply_count": 0, "like_count": 1, "quote_count": 0}, "in_reply_to_user_id": "367866510", "created_at": "2018-10-13T02:48:53.000Z", "lang": "lt", "author_id": "49640738", "text": "@jkmcnary1 Genius"}], "meta": {"newest_id": "1050945152754339840", "oldest_id": "1050941415105200128", "result_count": 2}}