{"data": [{"lang": "en", "text": "@NidhiPallooza I didn\u2019t get a call or a FaceTime??????", "public_metrics": {"retweet_count": 0, "reply_count": 1, "like_count": 0, "quote_count": 0}, "id": "1029920751091109894", "author_id": "191203731", "in_reply_to_user_id": "188446938", "created_at": "2018-08-16T02:40:16.000Z"}, {"lang": "en", "text": "@NidhiPallooza You\u2019re welcome \ud83d\ude09", "public_metrics": {"retweet_count": 0, "reply_count": 1, "like_count": 0, "quote_count": 0}, "id": "1029920085748707329", "author_id": "191203731", "in_reply_to_user_id": "188446938", "created_at": "2018-08-16T02:37:38.000Z"}, {"lang": "en", "text": "@NidhiPallooza HAPPY BIRTHDAY NID LETS GET DRUNK", "public_metrics": {"retweet_count": 0, "reply_count": 1, "like_count": 0, "quote_count": 0}, "id": "1029919998511333378", "author_id": "172273790", "in_reply_to_user_id": "188446938", "created_at": "2018-08-16T02:37:17.000Z"}], "meta": {"newest_id": "1029920751091109894", "oldest_id": "1029919998511333378", "result_count": 3}}