{"data": [{"in_reply_to_user_id": "16510838", "lang": "ht", "text": "@sugarscape \n\nKeepingUpWithTheKalderians\ud83d\udc4c\ud83d\udc4c\ud83d\udc4c\ud83d\udc4c\ud83d\udc4c\ud83d\udc4c\n\ud83d\udc8b\ud83d\udc8b\ud83d\udc8b\ud83d\udc8b\ud83d\udc8b\ud83d\udc8b\ud83d\udc8b\ud83d\udc8b\ud83d\udc8b\n@TheKalderians\u2764\ufe0f\u2764\ufe0f\nKeepingUpWithTheKalderians\ud83d\udc4c\ud83d\udc4c\ud83d\udc4c\ud83d\udc4c\ud83d\udc4c\ud83d\udc4c\n\ud83d\udc8b\ud83d\udc8b\ud83d\udc8b\ud83d\udc8b\ud83d\udc8b\ud83d\udc8b\ud83d\udc8b\ud83d\udc8b\ud83d\udc8b\n@TheKalderians\u2764\ufe0f\u2764\ufe0f", "public_metrics": {"retweet_count": 0, "reply_count": 0, "like_count": 0, "quote_count": 0}, "id": "658304277656416256", "created_at": "2015-10-25T15:29:05.000Z", "author_id": "3367301112"}], "meta": {"newest_id": "658304277656416256", "oldest_id": "658304277656416256", "result_count": 1}}