{"data": [{"public_metrics": {"retweet_count": 0, "reply_count": 0, "like_count": 0, "quote_count": 0}, "text": "@hungryheaux RIGHT HAHAHA THATS SO FUNNY TO ME. BUT THEY CUTE THO", "created_at": "2015-02-18T06:20:25.000Z", "author_id": "234638999", "lang": "en", "in_reply_to_user_id": "1368072618", "id": "567931625889247233"}, {"public_metrics": {"retweet_count": 1, "reply_count": 0, "like_count": 0, "quote_count": 0}, "text": "@xxdemigods I didn't know that part, that's so funny", "created_at": "2015-02-18T06:19:55.000Z", "author_id": "1368072618", "lang": "en", "in_reply_to_user_id": "234638999", "id": "567931499967852544"}, {"public_metrics": {"retweet_count": 0, "reply_count": 1, "like_count": 0, "quote_count": 0}, "text": "@xxdemigods LMAO KARMA BITCH \ud83d\ude02", "created_at": "2015-02-18T06:19:41.000Z", "author_id": "1368072618", "lang": "en", "in_reply_to_user_id": "234638999", "id": "567931440819777536"}, {"public_metrics": {"retweet_count": 0, "reply_count": 2, "like_count": 0, "quote_count": 0}, "text": "@hungryheaux she ends up with her ex bf's, ex gf. he played them both with each other. and now they had the last laugh LMAO.", "created_at": "2015-02-18T06:14:55.000Z", "author_id": "234638999", "lang": "en", "in_reply_to_user_id": "1368072618", "id": "567930241311735808"}, {"public_metrics": {"retweet_count": 0, "reply_count": 0, "like_count": 0, "quote_count": 0}, "text": "@hungryheaux lmao what! why do i feel like im the last one to know?!", "created_at": "2015-02-18T06:14:20.000Z", "author_id": "234638999", "lang": "en", "in_reply_to_user_id": "1368072618", "id": "567930092237803520"}, {"public_metrics": {"retweet_count": 0, "reply_count": 0, "like_count": 0, "quote_count": 0}, "text": "@hungryheaux http://t.co/M4HUNHfHrs", "created_at": "2015-02-18T06:05:28.000Z", "author_id": "234638999", "lang": "und", "in_reply_to_user_id": "234638999", "id": "567927861929234432"}], "meta": {"newest_id": "567931625889247233", "oldest_id": "567927861929234432", "result_count": 6}}