{"data": [{"lang": "und", "text": "@eljay25thleo \ud83d\ude02\ud83d\ude02", "public_metrics": {"retweet_count": 0, "reply_count": 0, "like_count": 0, "quote_count": 0}, "id": "1359328888401367043", "author_id": "3466503319", "in_reply_to_user_id": "1266435243520786432", "created_at": "2021-02-10T02:30:36.000Z"}, {"lang": "und", "text": "@_RAEofsunshine8 \ud83d\ude02\ud83d\ude02", "public_metrics": {"retweet_count": 0, "reply_count": 0, "like_count": 1, "quote_count": 0}, "id": "1359328845648850945", "author_id": "3466503319", "in_reply_to_user_id": "1275241617876803590", "created_at": "2021-02-10T02:30:26.000Z"}, {"lang": "en", "text": "@faithstreet08 u got the....lord", "public_metrics": {"retweet_count": 0, "reply_count": 1, "like_count": 0, "quote_count": 0}, "id": "1359325575404519425", "author_id": "1266435243520786432", "in_reply_to_user_id": "3466503319", "created_at": "2021-02-10T02:17:26.000Z"}, {"lang": "en", "text": "@faithstreet08 *before", "public_metrics": {"retweet_count": 0, "reply_count": 1, "like_count": 0, "quote_count": 0}, "id": "1359324739853049861", "author_id": "1275241617876803590", "in_reply_to_user_id": "3466503319", "created_at": "2021-02-10T02:14:07.000Z"}], "meta": {"newest_id": "1359328888401367043", "oldest_id": "1359324739853049861", "result_count": 4}}