{"data": [{"text": "@leseeta It\u2019s like a horror movie playing out in real time.", "public_metrics": {"retweet_count": 0, "reply_count": 0, "like_count": 0, "quote_count": 0}, "in_reply_to_user_id": "166627642", "lang": "en", "created_at": "2021-03-23T01:40:15.000Z", "author_id": "1036434026", "id": "1374174118032125953"}, {"text": "@IAmEzekiel336 I had a feeling they would turn into super spreaders.", "public_metrics": {"retweet_count": 0, "reply_count": 1, "like_count": 1, "quote_count": 0}, "in_reply_to_user_id": "1036434026", "lang": "en", "created_at": "2021-03-23T01:34:11.000Z", "author_id": "166627642", "id": "1374172590118408195"}, {"text": "*makes reference to...", "public_metrics": {"retweet_count": 0, "reply_count": 0, "like_count": 1, "quote_count": 0}, "in_reply_to_user_id": "1036434026", "lang": "en", "created_at": "2021-03-22T18:23:09.000Z", "author_id": "1036434026", "id": "1374064120320962566"}, {"text": "2 \n1st video @jdfarag makes a vaccine scientist who previously worked for GAVI/Gates Foundation.\n\n2nd video is interview with the Gateses \n\nThese revelations were given to me via the Holy Spirit months ago. \n\nhttps://t.co/MKZAwhCX2x\n\nhttps://t.co/x7ysapm3iI", "public_metrics": {"retweet_count": 1, "reply_count": 1, "like_count": 5, "quote_count": 1}, "in_reply_to_user_id": "1036434026", "lang": "en", "created_at": "2021-03-22T17:55:42.000Z", "author_id": "1036434026", "id": "1374057209341083650"}], "meta": {"newest_id": "1374174118032125953", "oldest_id": "1374057209341083650", "result_count": 4}}