{"data": [{"in_reply_to_user_id": "1274666662420074497", "public_metrics": {"retweet_count": 0, "reply_count": 0, "like_count": 0, "quote_count": 0}, "lang": "en", "id": "1387469123844591616", "created_at": "2021-04-28T18:09:51.000Z", "text": "@tv9kannada @publictvnews @AsianetNewsSN @News18Kannada @Vijaykarnataka @prajavani @BangaloreMirror @BangaloreTimes1 \nU people have to ask this to @mla_sudhakar n @CMofKarnataka ! Lakhs of 18 plus ppl r getting registered now. Will the govt get sufficient #vaccines for em?", "author_id": "1274666662420074497"}], "meta": {"newest_id": "1387469123844591616", "oldest_id": "1387469123844591616", "result_count": 1}}