{"data": [{"id": "1036741088541900800", "text": "@hgtv https://t.co/eAHWI22Xyf", "in_reply_to_user_id": "20188834", "created_at": "2018-09-03T22:21:51.000Z", "author_id": "1028706126379003904", "public_metrics": {"retweet_count": 0, "reply_count": 0, "like_count": 0, "quote_count": 0}, "lang": "und"}, {"id": "1035361075590574080", "text": "@hgtv Loved it, been watching For long time. love the transformations", "in_reply_to_user_id": "20188834", "created_at": "2018-08-31T02:58:11.000Z", "author_id": "2458917409", "public_metrics": {"retweet_count": 0, "reply_count": 0, "like_count": 0, "quote_count": 0}, "lang": "en"}], "meta": {"newest_id": "1036741088541900800", "oldest_id": "1035361075590574080", "result_count": 2}}