{"data": [{"public_metrics": {"retweet_count": 0, "reply_count": 1, "like_count": 1, "quote_count": 0}, "lang": "en", "text": "@marley_casale Wow you\u2019re famous", "created_at": "2018-07-15T15:29:41.000Z", "id": "1018517969956212741", "author_id": "250943594", "in_reply_to_user_id": "784399849911361537"}, {"public_metrics": {"retweet_count": 0, "reply_count": 0, "like_count": 2, "quote_count": 0}, "lang": "en", "text": "@marley_casale We\u2019ve always called him happy hands in my family. Legend", "created_at": "2018-07-15T00:15:34.000Z", "id": "1018287921764462594", "author_id": "19619475", "in_reply_to_user_id": "784399849911361537"}, {"public_metrics": {"retweet_count": 0, "reply_count": 0, "like_count": 0, "quote_count": 0}, "lang": "en", "text": "@marley_casale Young king", "created_at": "2018-07-14T20:27:13.000Z", "id": "1018230458486751233", "author_id": "320428870", "in_reply_to_user_id": "784399849911361537"}], "meta": {"newest_id": "1018517969956212741", "oldest_id": "1018230458486751233", "result_count": 3}}