{"contributors": null, "truncated": false, "text": "@memo_ryne @kaatje36 Pooootin LURVES #RoughSex", "in_reply_to_status_id": 576809327287246848, "id": 576809561408991232, "favorite_count": 2, "source": "<a href=\"http://twitter.com\" rel=\"nofollow\">Twitter Web Client</a>", "retweeted": false, "coordinates": null, "entities": {"symbols": [], "user_mentions": [{"id": 2938651047, "indices": [0, 10], "id_str": "2938651047", "screen_name": "memo_ryne", "name": "memo Ryne"}, {"id": 19024010, "indices": [11, 20], "id_str": "19024010", "screen_name": "kaatje36", "name": "Kaatje Kabelkrant"}], "hashtags": [{"indices": [37, 46], "text": "RoughSex"}], "urls": []}, "in_reply_to_screen_name": "memo_ryne", "id_str": "576809561408991232", "retweet_count": 0, "in_reply_to_user_id": 2938651047, "favorited": false, "user": {"follow_request_sent": false, "profile_use_background_image": true, "profile_text_color": "333333", "default_profile_image": false, "id": 315788583, "profile_background_image_url_https": "https://pbs.twimg.com/profile_background_images/359277754/14610_1_other_wallpapers_anonymous.jpg", "verified": false, "profile_location": null, "profile_image_url_https": "https://pbs.twimg.com/profile_images/1976638488/532628601_normal.png", "profile_sidebar_fill_color": "C0DFEC", "entities": {"description": {"urls": []}}, "followers_count": 11386, "profile_sidebar_border_color": "FFFFFF", "id_str": "315788583", "profile_background_color": "F5F9FA", "listed_count": 175, "is_translation_enabled": false, "utc_offset": 3600, "statuses_count": 53443, "description": "A #LoneWolf... *Dance like a butterfly.. stings like a bee*  #0FucksSec", "friends_count": 178, "location": "OZ but currently on walkabouts", "profile_link_color": "0084B4", "profile_image_url": "http://pbs.twimg.com/profile_images/1976638488/532628601_normal.png", "following": false, "geo_enabled": false, "profile_background_image_url": "http://pbs.twimg.com/profile_background_images/359277754/14610_1_other_wallpapers_anonymous.jpg", "name": "Domainer", "lang": "en", "profile_background_tile": false, "favourites_count": 33318, "screen_name": "DomainerAnon", "notifications": false, "url": null, "created_at": "Sun Jun 12 13:02:32 +0000 2011", "contributors_enabled": false, "time_zone": "London", "protected": false, "default_profile": false, "is_translator": false}, "geo": null, "in_reply_to_user_id_str": "2938651047", "lang": "in", "created_at": "Sat Mar 14 18:18:10 +0000 2015", "in_reply_to_status_id_str": "576809327287246848", "place": null}
