{"data": [{"created_at": "2018-12-07T06:43:03.000Z", "lang": "en", "in_reply_to_user_id": "3363187822", "text": "@thetalko @YouTube delete this tweet and this article. selena hasn\u2019t spoken to ANYONE and definitely not to you. it\u2019s incredible the lines you\u2019d cross just to get more visibility. start being respectful and professional already.", "id": "1070931679265611778", "public_metrics": {"retweet_count": 0, "reply_count": 0, "like_count": 0, "quote_count": 0}, "author_id": "2992628511"}, {"created_at": "2018-12-06T21:49:17.000Z", "lang": "en", "in_reply_to_user_id": "3363187822", "text": "@thetalko @YouTube fuck u, this is fake!", "id": "1070797350069768192", "public_metrics": {"retweet_count": 0, "reply_count": 0, "like_count": 2, "quote_count": 0}, "author_id": "705102634563272704"}], "meta": {"newest_id": "1070931679265611778", "oldest_id": "1070797350069768192", "result_count": 2}}