{"data": [{"in_reply_to_user_id": "474769483", "author_id": "714614171539668992", "lang": "en", "text": "@LadyGagaTopNews She most certainly is not. Have you ever had chronic pain? She is trying to get through a day of doing her job and living", "id": "927200490873483265", "public_metrics": {"retweet_count": 0, "reply_count": 0, "like_count": 0, "quote_count": 0}, "created_at": "2017-11-05T15:46:38.000Z"}], "meta": {"newest_id": "927200490873483265", "oldest_id": "927200490873483265", "result_count": 1}}