{"data": [{"public_metrics": {"retweet_count": 0, "reply_count": 0, "like_count": 0, "quote_count": 0}, "lang": "en", "text": "@justmeDayana me too, lmao \ud83e\udd2a", "created_at": "2018-09-05T11:25:50.000Z", "id": "1037300770570481664", "author_id": "418092029", "in_reply_to_user_id": "172767770"}, {"public_metrics": {"retweet_count": 0, "reply_count": 0, "like_count": 0, "quote_count": 0}, "lang": "en", "text": "@justmeDayana welcome to the club, bitch \ud83d\ude18", "created_at": "2018-09-05T11:23:18.000Z", "id": "1037300131303968768", "author_id": "418092029", "in_reply_to_user_id": "172767770"}, {"public_metrics": {"retweet_count": 0, "reply_count": 0, "like_count": 1, "quote_count": 0}, "lang": "en", "text": "@justmeDayana wHo I aM? A sPoTiFy UsEr?", "created_at": "2018-09-05T11:21:43.000Z", "id": "1037299735672053762", "author_id": "418092029", "in_reply_to_user_id": "172767770"}], "meta": {"newest_id": "1037300770570481664", "oldest_id": "1037299735672053762", "result_count": 3}}